benvy/BenvyConfig.py
benvy/container/dicontainer.py
benvy/databricks/BinExecutableFlagSetter.py
benvy/databricks/DatabricksConnectConfigCreator.py
benvy/databricks/DatabricksConnectDetector.py
benvy/databricks/DatabricksContext.py
benvy/databricks/api/WorkspaceApiFactory.py
benvy/databricks/dbutils/DBUtilsResolver.py
benvy/databricks/detector.py
benvy/databricks/notebook/CommandConverter.py
benvy/databricks/notebook/CommandsConverter.py
benvy/databricks/notebook/NotebookConverter.py
benvy/databricks/repos/bootstrap.py
benvy/databricks/repos/config/BootstrapConfig.py
benvy/databricks/repos/config/BootstrapInstallConfig.py
benvy/databricks/repos/config/BootstrapInstallDevConfig.py
benvy/databricks/repos/config/BootstrapSetupEnvConfig.py
benvy/databricks/repos/config/PoetrySetupConfig.py
benvy/databricks/repos/export/ExportObject.py
benvy/databricks/repos/export/NotebooksAndFilesExporter.py
benvy/databricks/repos/install/DbrDependenciesChecker.py
benvy/databricks/repos/install/DbrPythonChecker.py
benvy/databricks/repos/install/PackageInstaller.py
benvy/databricks/repos/install/PoetryDownloader.py
benvy/databricks/repos/install/PoetryInstallScriptDownloader.py
benvy/databricks/repos/install/PoetryInstaller.py
benvy/databricks/repos/poetry/PoetryWrapper.py
benvy/databricks/repos/poetry/magic.py
benvy/databricks/repos/poetry/setup.py
benvy/databricks/repos/project_root_resolver.py
benvy/databricks/repos/pylint/PylintExecutableResolver.py
benvy/databricks/repos/pylint/PylintHTMLDisplayer.py
benvy/databricks/repos/pylint/PylintResultsEnhancer.py
benvy/databricks/repos/pylint/PylintWrapper.py
benvy/databricks/repos/pylint/icons/file_icon.base64
benvy/databricks/repos/pylint/icons/notebook_icon.base64
benvy/databricks/repos/pylint/icons/question_mark_icon.base64
benvy/databricks/repos/pylint/magic.py
benvy/databricks/repos/runner/BootstrapRunner.py
benvy/databricks/repos/setup/BootstrapEnvSetter.py
benvy/databricks/repos/setup/ProjectRootDirSetter.py
benvy-1.4.8.dist-info/METADATA
benvy-1.4.8.dist-info/WHEEL
benvy-1.4.8.dist-info/entry_points.txt
benvy-1.4.8.dist-info/RECORD
